unrealon_browser/README.md
unrealon_browser/__init__.py
unrealon_browser/cli/__init__.py
unrealon_browser/cli/browser_cli.py
unrealon_browser/cli/cookies_cli.py
unrealon_browser/cli/interactive_mode.py
unrealon_browser/cli/main.py
unrealon_browser/core/__init__.py
unrealon_browser/core/browser_manager.py
unrealon_browser/dto/__init__.py
unrealon_browser/dto/bot_detection.py
unrealon_browser/dto/models/config.py
unrealon_browser/dto/models/core.py
unrealon_browser/dto/models/dataclasses.py
unrealon_browser/dto/models/detection.py
unrealon_browser/dto/models/enums.py
unrealon_browser/dto/models/statistics.py
unrealon_browser/managers/__init__.py
unrealon_browser/managers/captcha.py
unrealon_browser/managers/cookies.py
unrealon_browser/managers/data_extraction_manager.py
unrealon_browser/managers/logger_bridge.py
unrealon_browser/managers/page_wait_manager.py
unrealon_browser/managers/profile.py
unrealon_browser/managers/script_manager.py
unrealon_browser/stealth/__init__.py
unrealon_browser/stealth/bypass_techniques.py
unrealon_browser/stealth/manager.py
unrealon_browser/stealth/nodriver_stealth.py
unrealon_browser/stealth/playwright_stealth.py
unrealon_browser/stealth/scanner_tester.py
unrealon_browser/stealth/undetected_chrome.py
unrealon_core/__init__.py
unrealon_core/version.py
unrealon_core/config/__init__.py
unrealon_core/config/environment.py
unrealon_core/config/urls.py
unrealon_core/enums/__init__.py
unrealon_core/enums/events.py
unrealon_core/enums/jobs.py
unrealon_core/enums/status.py
unrealon_core/enums/types.py
unrealon_core/error_handling/__init__.py
unrealon_core/error_handling/circuit_breaker.py
unrealon_core/error_handling/error_context.py
unrealon_core/error_handling/recovery.py
unrealon_core/error_handling/retry.py
unrealon_core/exceptions/__init__.py
unrealon_core/exceptions/base.py
unrealon_core/exceptions/communication.py
unrealon_core/exceptions/driver.py
unrealon_core/exceptions/proxy.py
unrealon_core/exceptions/task.py
unrealon-2.0.35.dist-info/LICENSE
unrealon-2.0.35.dist-info/METADATA
unrealon-2.0.35.dist-info/WHEEL
unrealon-2.0.35.dist-info/entry_points.txt
unrealon-2.0.35.dist-info/top_level.txt
unrealon-2.0.35.dist-info/RECORD
