Metadata-Version: 2.1
Name: unrealon
Version: 2.0.35
Summary: Enterprise-grade web scraping platform with AI-powered automation and real-time orchestration capabilities
Author-email: UnrealOn Team <team@unrealon.com>
License: MIT
Project-URL: Homepage, https://unrealon.com
Project-URL: Repository, https://github.com/markolofsen/unrealon-parser-amazon
Project-URL: Documentation, https://unrealon.com
Keywords: web-scraping,automation,ai,browser,driver,parsing,orchestration
Classifier: Development Status :: 4 - Beta
Classifier: Intended Audience :: Developers
Classifier: Programming Language :: Python :: 3
Classifier: Programming Language :: Python :: 3.10
Classifier: Programming Language :: Python :: 3.11
Classifier: Programming Language :: Python :: 3.12
Classifier: Topic :: Internet :: WWW/HTTP
Classifier: Topic :: Software Development :: Libraries :: Python Modules
Classifier: Topic :: Software Development :: Testing
Classifier: Topic :: Scientific/Engineering :: Artificial Intelligence
Requires-Python: <4.0,>=3.10
License-File: LICENSE
Requires-Dist: pydantic>=2.0.0
Requires-Dist: typing-extensions>=4.0.0
Requires-Dist: selenium>=4.15.0
Requires-Dist: playwright>=1.40.0
Requires-Dist: undetected-chromedriver>=3.5.0
Requires-Dist: fake-useragent>=1.4.0
Requires-Dist: aiofiles>=23.0.0
Requires-Dist: click>=8.1.0
Requires-Dist: aiohttp>=3.8.0
Requires-Dist: httpx>=0.23.0
Requires-Dist: beautifulsoup4>=4.13.5
Requires-Dist: pydantic-yaml>=1.6.0
Requires-Dist: rich>=13.0.0
Requires-Dist: pyyaml>=6.0
Requires-Dist: python-socketio>=5.0
Requires-Dist: python-dateutil>=2.8
Requires-Dist: playwright-stealth>=2.0.0
Requires-Dist: questionary>=2.0.0
Requires-Dist: asyncio-extras>=1.3.0
Requires-Dist: pathlib2>=2.3.0
Requires-Dist: openai>=1.0.0
Requires-Dist: tiktoken>=0.9.0
Requires-Dist: fast-langdetect>=0.3.2
Requires-Dist: langid>=1.1.6
Requires-Dist: langdetect>=1.0.9
Requires-Dist: cachetools>=5.3.0
Requires-Dist: python-dotenv>=1.0.0
Requires-Dist: tomlkit>=0.13.3
Provides-Extra: ai
Requires-Dist: openai>=1.0.0; extra == "ai"
Requires-Dist: tiktoken>=0.9.0; extra == "ai"
Requires-Dist: fast-langdetect>=0.3.2; extra == "ai"
Requires-Dist: langid>=1.1.6; extra == "ai"
Requires-Dist: langdetect>=1.0.9; extra == "ai"
Provides-Extra: browser
Requires-Dist: selenium>=4.15.0; extra == "browser"
Requires-Dist: playwright>=1.40.0; extra == "browser"
Requires-Dist: undetected-chromedriver>=3.5.0; extra == "browser"
Requires-Dist: playwright-stealth>=2.0.0; extra == "browser"
Provides-Extra: dev
Requires-Dist: pytest>=7.0.0; extra == "dev"
Requires-Dist: pytest-asyncio>=0.21.0; extra == "dev"
Requires-Dist: pytest-cov>=4.0.0; extra == "dev"
Requires-Dist: pytest-mock>=3.12.0; extra == "dev"
Requires-Dist: pytest-benchmark>=4.0.0; extra == "dev"
Requires-Dist: pytest-html>=4.0.0; extra == "dev"
Requires-Dist: pytest-xdist>=3.3.0; extra == "dev"
Requires-Dist: pytest-timeout>=2.1.0; extra == "dev"
Requires-Dist: pytest-playwright>=0.4.0; extra == "dev"
Requires-Dist: black>=23.0.0; extra == "dev"
Requires-Dist: isort>=5.12.0; extra == "dev"
Requires-Dist: mypy>=1.0.0; extra == "dev"
Requires-Dist: ruff>=0.1.0; extra == "dev"
Requires-Dist: build>=1.0.0; extra == "dev"
Requires-Dist: twine>=4.0.0; extra == "dev"
Requires-Dist: questionary>=2.1.0; extra == "dev"
Requires-Dist: tomlkit>=0.13.3; extra == "dev"
Requires-Dist: bandit>=1.7.5; extra == "dev"
Requires-Dist: safety>=2.3.0; extra == "dev"
Requires-Dist: pylint>=2.17.0; extra == "dev"
Requires-Dist: locust>=2.0.0; extra == "dev"
Requires-Dist: responses>=0.23.0; extra == "dev"
Requires-Dist: aioresponses>=0.7.4; extra == "dev"
Requires-Dist: pre-commit>=3.3.0; extra == "dev"
Requires-Dist: types-PyYAML>=6.0; extra == "dev"
Requires-Dist: types-python-dateutil>=2.8; extra == "dev"
Provides-Extra: full
Requires-Dist: selenium>=4.15.0; extra == "full"
Requires-Dist: playwright>=1.40.0; extra == "full"
Requires-Dist: undetected-chromedriver>=3.5.0; extra == "full"
Requires-Dist: playwright-stealth>=2.0.0; extra == "full"
Requires-Dist: openai>=1.0.0; extra == "full"
Requires-Dist: tiktoken>=0.9.0; extra == "full"
Requires-Dist: fast-langdetect>=0.3.2; extra == "full"
Requires-Dist: langid>=1.1.6; extra == "full"
Requires-Dist: langdetect>=1.0.9; extra == "full"
